<?xml version="1.0" encoding="UTF-8" ?>
<!DOCTYPE tiles-definitions PUBLIC
       "-//Apache Software Foundation//DTD Tiles Configuration 2.0//EN"
       "http://tiles.apache.org/dtds/tiles-config_2_0.dtd">
<tiles-definitions>
     <definition name="/mypage/deliveryInquiry" extends="mainLayout">
       <put-attribute name="title" value="배송조회 페이지" />
       <put-attribute name="body" value="/WEB-INF/views/mypage/deliveryInquiry.jsp" />
    </definition>
   <definition name="/mypage/orderCancel" extends="mainLayout">
       <put-attribute name="title" value="주문취소 페이지" />
       <put-attribute name="body" value="/WEB-INF/views/mypage/orderCancel.jsp" />
    </definition>
    <definition name="/mypage/orderConfirm" extends="nosidebarLayout">
       <put-attribute name="title" value="주문하기 페이지" />
       <put-attribute name="body" value="/WEB-INF/views/mypage/orderConfirm.jsp" />
    </definition>
    <definition name="/mypage/orderDetail" extends="mainLayout">
       <put-attribute name="title" value="주문상세 페이지" />
       <put-attribute name="body" value="/WEB-INF/views/mypage/orderDetail.jsp" />
    </definition>
    <definition name="/mypage/orderList" extends="mainLayout">
       <put-attribute name="title" value="주문내역 페이지" />
       <put-attribute name="body" value="/WEB-INF/views/mypage/orderList.jsp" />
    </definition>
</tiles-definitions>


